mcp_ui/__init__.py
mcp_ui/core.py
mcp_ui-0.1.2.dist-info/METADATA
mcp_ui-0.1.2.dist-info/WHEEL
mcp_ui-0.1.2.dist-info/licenses/LICENSE
mcp_ui-0.1.2.dist-info/RECORD
