Metadata-Version: 2.4
Name: mcp-ui
Version: 0.1.2
Summary: A Python SDK for building MCP UI resources (iframe, panels, text blocks, etc.) in a type-safe way.
Project-URL: Homepage, https://github.com/jameszokah/mcp-ui
Project-URL: Repository, https://github.com/jameszokah/mcp-ui
Project-URL: Issues, https://github.com/jameszokah/mcp-ui/issues
Project-URL: Documentation, https://github.com/jameszokah/mcp-ui#readme
Author-email: James Zokah <jameszokah@gmail.com>
License: MIT
License-File: LICENSE
Keywords: agents,chat,iframe,mcp,python,sdk,ui
Classifier: Development Status :: 3 - Alpha
Classifier: License :: OSI Approved :: MIT License
Classifier: Operating System :: OS Independent
Classifier: Programming Language :: Python :: 3
Classifier: Programming Language :: Python :: 3.9
Classifier: Programming Language :: Python :: 3.10
Classifier: Programming Language :: Python :: 3.11
Classifier: Programming Language :: Python :: 3.12
Requires-Python: >=3.9
